anahita/WikiTextMapper.py
anahita/__init__.py
anahita-0.1.1.dist-info/WHEEL
anahita-0.1.1.dist-info/METADATA
anahita-0.1.1.dist-info/RECORD
